MANIFEST.in
README.md
setup.py
Flask_Statics_Helper.egg-info/PKG-INFO
Flask_Statics_Helper.egg-info/SOURCES.txt
Flask_Statics_Helper.egg-info/dependency_links.txt
Flask_Statics_Helper.egg-info/not-zip-safe
Flask_Statics_Helper.egg-info/requires.txt
Flask_Statics_Helper.egg-info/top_level.txt
flask_statics/__init__.py
flask_statics/helpers.py
flask_statics/resource_base.py
flask_statics/resource_definitions.py
flask_statics/resource_definitions_angular.py
flask_statics/static/BootstrapValidator-0.5.0/README.md
flask_statics/static/BootstrapValidator-0.5.0/css/bootstrapValidator.css
flask_statics/static/BootstrapValidator-0.5.0/css/bootstrapValidator.min.css
flask_statics/static/BootstrapValidator-0.5.0/js/bootstrapValidator.js
flask_statics/static/BootstrapValidator-0.5.0/js/bootstrapValidator.min.js
flask_statics/static/BootstrapValidator-0.5.0/js/language/de_DE.js
flask_statics/static/BootstrapValidator-0.5.0/js/language/en_US.js
flask_statics/static/BootstrapValidator-0.5.0/js/language/es_CL.js
flask_statics/static/BootstrapValidator-0.5.0/js/language/hu_HU.js
flask_statics/static/BootstrapValidator-0.5.0/js/language/vi_VN.js
flask_statics/static/BootstrapValidator-0.5.0/js/language/zh_CN.js
flask_statics/static/BootstrapValidator-0.5.0/js/language/zh_TW.js
flask_statics/static/DataTables-1.10.0/Readme.md
flask_statics/static/DataTables-1.10.0/license.txt
flask_statics/static/DataTables-1.10.0/css/jquery.dataTables.css
flask_statics/static/DataTables-1.10.0/css/jquery.dataTables.min.css
flask_statics/static/DataTables-1.10.0/css/jquery.dataTables_themeroller.css
flask_statics/static/DataTables-1.10.0/css/jquery.dataTables_themeroller.min.css
flask_statics/static/DataTables-1.10.0/extensions/AutoFill/Readme.txt
flask_statics/static/DataTables-1.10.0/extensions/AutoFill/css/dataTables.autoFill.css
flask_statics/static/DataTables-1.10.0/extensions/AutoFill/css/dataTables.autoFill.min.css
flask_statics/static/DataTables-1.10.0/extensions/AutoFill/images/filler.png
flask_statics/static/DataTables-1.10.0/extensions/AutoFill/js/dataTables.autoFill.js
flask_statics/static/DataTables-1.10.0/extensions/AutoFill/js/dataTables.autoFill.min.js
flask_statics/static/DataTables-1.10.0/extensions/ColReorder/Readme.txt
