Metadata-Version: 1.1
Name: Flask-Statics-Helper
Version: 0.3.0
Summary: Provides Bootstrap3 and other static resources in a modular fashion.
Home-page: https://github.com/Robpol86/Flask-Statics-Helper
Author: @Robpol86
Author-email: robpol86@gmail.com
License: MIT
Keywords: flask
Platform: UNKNOWN
Classifier: Development Status :: 3 - Alpha
Classifier: Environment :: Web Environment
Classifier: Framework :: Flask
Classifier: Intended Audience :: Developers
Classifier: Topic :: Software Development :: Build Tools
Classifier: License :: OSI Approved :: MIT License
Classifier: Operating System :: POSIX
Classifier: Programming Language :: Python :: 2.6
Classifier: Programming Language :: Python :: 2.7
Classifier: Programming Language :: Python :: 3.3
Classifier: Programming Language :: Python :: 3.4
